pySidraData/__init__.py
pySidraData/client.py
pySidraData/models.py
pySidraData/version.py
tests/__init__.py
tests/test_client.py
tests/test_models.py
pySidraData-0.1.2.dist-info/LICENSE
pySidraData-0.1.2.dist-info/METADATA
pySidraData-0.1.2.dist-info/WHEEL
pySidraData-0.1.2.dist-info/top_level.txt
pySidraData-0.1.2.dist-info/RECORD
