Metadata-Version: 2.1
Name: pySidraData
Version: 0.1.2
Summary: A Python client for interacting with IBGE API for aggregate data.
Author: Fernando Barbosa
Author-email: Fernando Barbosa <fernando.liaison@gmail.com>
License: MIT
Project-URL: Homepage, https://github.com/nandevers/pySidraData
Project-URL: Repository, https://github.com/nandevers/pySidraData
Keywords: IBGE,API,data,sidra
Classifier: Programming Language :: Python :: 3
Classifier: License :: OSI Approved :: MIT License
Classifier: Operating System :: OS Independent
License-File: LICENSE
Requires-Dist: requests==2.31.0
Requires-Dist: pandas==2.1.1
Requires-Dist: sidrapy==0.1.2
Provides-Extra: dev
Requires-Dist: pre-commit; extra == "dev"
Requires-Dist: flake8; extra == "dev"
Requires-Dist: black; extra == "dev"
Requires-Dist: isort; extra == "dev"
